aiohttp_mcp/__init__.py
aiohttp_mcp/app.py
aiohttp_mcp/core.py
aiohttp_mcp/streamable_http.py
aiohttp_mcp/streamable_http_manager.py
aiohttp_mcp/transport.py
aiohttp_mcp/types.py
aiohttp_mcp/utils/__init__.py
aiohttp_mcp/utils/discover.py
aiohttp_mcp-0.7.0.dist-info/METADATA
aiohttp_mcp-0.7.0.dist-info/WHEEL
aiohttp_mcp-0.7.0.dist-info/licenses/LICENSE
aiohttp_mcp-0.7.0.dist-info/RECORD
