Metadata-Version: 2.4
Name: aiohttp-mcp
Version: 0.7.0
Summary: Tools for building Model Context Protocol (MCP) servers on top of aiohttp
Project-URL: Homepage, https://github.com/kulapard/aiohttp-mcp
Project-URL: Repository, https://github.com/kulapard/aiohttp-mcp.git
Project-URL: Documentation, https://github.com/kulapard/aiohttp-mcp#readme
Author-email: Taras Drapalyuk <taras@drapalyuk.com>
License-Expression: MIT
License-File: LICENSE
Keywords: ai,aiohttp,async,llm,mcp,model-context-protocol,server
Classifier: Development Status :: 5 - Production/Stable
Classifier: Intended Audience :: Developers
Classifier: License :: OSI Approved :: MIT License
Classifier: Programming Language :: Python :: 3
Classifier: Programming Language :: Python :: 3.10
Classifier: Programming Language :: Python :: 3.11
Classifier: Programming Language :: Python :: 3.12
Classifier: Programming Language :: Python :: 3.13
Classifier: Programming Language :: Python :: 3.14
Classifier: Topic :: Internet :: WWW/HTTP :: HTTP Servers
Classifier: Topic :: Scientific/Engineering :: Artificial Intelligence
Classifier: Topic :: Software Development :: Libraries :: Python Modules
Requires-Python: >=3.10
Requires-Dist: aiohttp-sse<3.0.0,>=2.2.0
Requires-Dist: aiohttp<4.0.0,>=3.9.0
Requires-Dist: anyio<5.0.0,>=4.9.0
Requires-Dist: mcp<2.0.0,>=1.24.0
